xia_token_flask/__init__.py
xia_token_flask/token.cpython-311-darwin.so
xia_token_flask-0.1.17.dist-info/LICENSE.txt
xia_token_flask-0.1.17.dist-info/METADATA
xia_token_flask-0.1.17.dist-info/WHEEL
xia_token_flask-0.1.17.dist-info/top_level.txt
xia_token_flask-0.1.17.dist-info/RECORD
