Metadata-Version: 2.1
Name: xia-token-flask
Version: 0.1.17
Summary: UNKNOWN
Home-page: https://develop.x-i-a.com/docs/xia-token-flask/0.1.17/index.html
Author: X-I-A
Author-email: admin@x-i-a.com
License: UNKNOWN
Platform: UNKNOWN
Requires-Python: >=3.9
License-File: LICENSE.txt
Requires-Dist: Flask
Requires-Dist: PyJWT
Requires-Dist: xia-engine
